{
    "primitives": [
        "mlprimitives.custom.timeseries_preprocessing.time_segments_average",
        "sklearn.impute.SimpleImputer",
        "mlprimitives.custom.preprocessing.RangeScaler",
        "pyteller.primitives.estimators.lagged",
        "mlprimitives.custom.preprocessing.RangeUnscaler",
        "pandas.DataFrame",
        "pyteller.primitives.post_process.convert_date"

    ],
"init_params": {
        "mlprimitives.custom.timeseries_preprocessing.time_segments_average#1": {
            "time_column": "timestamp",
            "interval": 1800
        },

            "pyteller.primitives.estimators.lagged": {
            "shift": 10

        }
}
    ,
        "input_names": {
            "mlprimitives.custom.preprocessing.RangeUnscaler#1": {
                "X": "y_hat"
        },
            "pandas.DataFrame#1": {
                "index": "target_index",
                "X": "y_hat"
        },
            "pyteller.primitives.post_process.convert_date#1": {
                 "X": "y_hat"
        }
        },
    "output_names": {
         "pyteller.primitives.estimators.lagged#1": {
            "X": "y_hat"

        },
        "mlprimitives.custom.preprocessing.RangeUnscaler#1": {
            "X": "y_hat"
        },
        "pandas.DataFrame#1": {
            "X": "y_hat"
        }
    }
}

